drupaljsonapiclient/__init__.py
drupaljsonapiclient/common.py
drupaljsonapiclient/document.py
drupaljsonapiclient/exceptions.py
drupaljsonapiclient/filter.py
drupaljsonapiclient/objects.py
drupaljsonapiclient/relationships.py
drupaljsonapiclient/resourceobject.py
drupaljsonapiclient/session.py
drupaljsonapiclient-1.1.1.dist-info/LICENSE
drupaljsonapiclient-1.1.1.dist-info/METADATA
drupaljsonapiclient-1.1.1.dist-info/WHEEL
drupaljsonapiclient-1.1.1.dist-info/RECORD
