Metadata-Version: 2.1
Name: drupaljsonapiclient
Version: 1.1.1
Summary: Drupal CMS JSON:API client for Python.
Home-page: https://gitlab.com/martins-bruvelis/drupaljsonapiclient
Author: Martins Bruvelis
Author-email: martins.bruvelis@gmail.com
Requires-Python: >=3.8,<4.0
Classifier: Programming Language :: Python :: 3
Classifier: Programming Language :: Python :: 3.8
Classifier: Programming Language :: Python :: 3.9
Classifier: Programming Language :: Python :: 3.10
Classifier: Programming Language :: Python :: 3.11
Classifier: Programming Language :: Python :: 3.12
Provides-Extra: async
Requires-Dist: aiofiles (>=23.2.1,<24.0.0) ; extra == "async"
Requires-Dist: aiohttp (>=3.9.5,<4.0.0) ; extra == "async"
Requires-Dist: jsonschema (>=4.22.0,<5.0.0)
Requires-Dist: requests (>=2.31.0,<3.0.0)
Project-URL: Documentation, https://gitlab.com/martins-bruvelis/drupaljsonapiclient/-/blob/main/README.md
Project-URL: Repository, https://gitlab.com/martins-bruvelis/drupaljsonapiclient
